menta/__init__.py
menta/_core.py
menta/_utils.py
menta/errors.py
menta/py.typed
menta-0.0.1a2.dist-info/LICENSE
menta-0.0.1a2.dist-info/WHEEL
menta-0.0.1a2.dist-info/METADATA
menta-0.0.1a2.dist-info/RECORD
