Metadata-Version: 2.1
Name: menta
Version: 0.0.1a2
Summary: Secure, simple and easy to use API token format
Home-page: https://github.com/alexbakker/menta
License: MIT
Keywords: api,token,xchacha20,poly1305
Author: Alexander Bakker
Author-email: ab@alexbakker.me
Requires-Python: >=3.8,<4.0
Classifier: Development Status :: 3 - Alpha
Classifier: License :: OSI Approved :: MIT License
Classifier: Programming Language :: Python :: 3
Classifier: Programming Language :: Python :: 3.10
Classifier: Programming Language :: Python :: 3.8
Classifier: Programming Language :: Python :: 3.9
Classifier: Topic :: Security
Classifier: Topic :: Security :: Cryptography
Requires-Dist: PyNaCl (>=1.5.0,<2.0.0)
Project-URL: Documentation, https://github.com/alexbakker/menta
Project-URL: Repository, https://github.com/alexbakker/menta
